setup.py
pocketmiku/__init__.py
pocketmiku/amidi.py
pocketmiku/control.py
pocketmiku/notes.py
pocketmiku.egg-info/PKG-INFO
pocketmiku.egg-info/SOURCES.txt
pocketmiku.egg-info/dependency_links.txt
pocketmiku.egg-info/top_level.txt
pocketmiku/samples/__init__.py
pocketmiku/samples/kimigayo.py
pocketmiku/samples/ohmydarling.py
pocketmiku/tools/__init__.py
pocketmiku/tools/sendraw.py
pocketmiku/tools/setlyrics.py
pocketmiku/tools/test.py