Metadata-Version: 1.1
Name: pocketmiku
Version: 0.2.1
Summary: Tools to configure a Pocket Miku (NSX-39)
Home-page: https://github.com/klange/pocketmiku
Author: Kevin Lange
Author-email: klange@dakko.us
License: University of Illinois/NCSA Open Source License
Keywords: miku vocaloid pocketmiku nsx-39 midi audio
Platform: UNKNOWN
Classifier: Development Status :: 4 - Beta
Classifier: Topic :: Multimedia :: Sound/Audio :: MIDI
Classifier: Topic :: Multimedia :: Sound/Audio :: Sound Synthesis
Classifier: Topic :: Multimedia :: Sound/Audio :: Speech
Classifier: License :: OSI Approved :: University of Illinois/NCSA Open Source License
Classifier: Programming Language :: Python :: 2
Classifier: Programming Language :: Python :: 2.6
Classifier: Programming Language :: Python :: 2.7
